<Properties StartupConfiguration="{896B547F-02FB-48C8-8BFE-DDEE55C55E44}|Default">
  <MonoDevelop.Ide.ItemProperties.Assignment4.Android AndroidDesignerPreferredTheme="Theme.DeviceDefault.NoActionBar.Fullscreen" PreferredExecutionTarget="Android.Android_Accelerated_Oreo" />
  <MonoDevelop.Ide.ItemProperties.Assignment4.iOS automaticSigning="False" PreferredExecutionTarget="MonoDevelop.IPhone.IPhoneSimulatorTarget.2EA1C538-AB3E-4CDA-B14B-FB0C4C3D61DA" />
  <MonoDevelop.Ide.Workbench ActiveDocument="Assignment4Core/ViewModels/MapViewModel.cs">
    <Files>
      <File FileName="Assignment4Core/Services/PlacesAPIService.cs" Line="24" Column="1" />
      <File FileName="Assignment4Core/Services/IPlacesAPIService.cs" Line="15" Column="1" />
      <File FileName="Assignment4/Views/MapPage.xaml.cs" Line="50" Column="1" />
      <File FileName="Assignment4Core/ViewModels/MapViewModel.cs" Line="55" Column="1" />
      <File FileName="Assignment4/Views/MapPage.xaml" Line="20" Column="54" />
      <File FileName="Assignment4.iOS/Main.cs" Line="17" Column="1" />
      <File FileName="Assignment4Core/Models/PlacesOfInterest.cs" Line="22" Column="34" />
      <File FileName="Assignment4Core/Models/Restaurant.cs" Line="14" Column="10" />
      <File FileName="Assignment4Core/Models/Lodging.cs" Line="8" Column="24" />
      <File FileName="Assignment4Core/Models/Car_Rental.cs" Line="17" Column="1" />
      <File FileName="Assignment4.iOS/AppDelegate.cs" Line="32" Column="1" />
      <File FileName="Assignment4/App.xaml.cs" Line="16" Column="1" />
      <File FileName="Assignment4/obj/Debug/netstandard2.0/App.xaml.g.cs" Line="1" Column="1" />
      <File FileName="Assignment4/Views/MainPage.xaml.cs" Line="13" Column="1" />
      <File FileName="Assignment4/obj/Debug/netstandard2.0/Views/MainPage.xaml.g.cs" Line="1" Column="1" />
      <File FileName="Assignment4/Views/ItemsPage.xaml.cs" Line="22" Column="1" />
      <File FileName="Assignment4/Views/AboutPage.xaml.cs" Line="13" Column="1" />
      <File FileName="Assignment4Core/ViewModels/MainViewModel.cs" Line="20" Column="1" />
      <File FileName="Assignment4Core/App.cs" Line="25" Column="1" />
      <File FileName="Assignment4Core/app.config" Line="10" Column="1" />
    </Files>
  </MonoDevelop.Ide.Workbench>
  <MonoDevelop.Ide.DebuggingService.PinnedWatches />
  <MonoDevelop.Ide.Workspace ActiveConfiguration="Debug" />
  <MonoDevelop.Ide.DebuggingService.Breakpoints>
    <BreakpointStore />
  </MonoDevelop.Ide.DebuggingService.Breakpoints>
  <MultiItemStartupConfigurations />
</Properties>